pypeepa/__init__.py
pypeepa/checks/__init__.py
pypeepa/checks/checkEncoding.py
pypeepa/checks/checkIfListIsAllNone.py
pypeepa/checks/checkInputIsInt.py
pypeepa/debugging/__init__.py
pypeepa/debugging/initLogging.py
pypeepa/fileInteraction/__init__.py
pypeepa/fileInteraction/countTotalRows.py
pypeepa/fileInteraction/createDirectory.py
pypeepa/fileInteraction/listDir.py
pypeepa/fileInteraction/readData.py
pypeepa/fileInteraction/readJSON.py
pypeepa/fileInteraction/writeFile.py
pypeepa/optimisations/ProgressSaver.py
pypeepa/optimisations/__init__.py
pypeepa/optimisations/concurrentFutures.py
pypeepa/optimisations/processCSVInChunks.py
pypeepa/userInteraction/__init__.py
pypeepa/userInteraction/askHeaderForMultipleCSV.py
pypeepa/userInteraction/askSelectOptionQuestion.py
pypeepa/userInteraction/askSelectRangeQuestion.py
pypeepa/userInteraction/askYNQuestion.py
pypeepa/userInteraction/getFilePath.py
pypeepa/userInteraction/printArray.py
pypeepa/userInteraction/progressBarIterator.py
pypeepa/userInteraction/signature.py
pypeepa/utils/__init__.py
pypeepa/utils/loggingHandler.py
pypeepa/utils/measureTimeToRun.py
pypeepa-5.4.dist-info/METADATA
pypeepa-5.4.dist-info/WHEEL
pypeepa-5.4.dist-info/top_level.txt
pypeepa-5.4.dist-info/RECORD
