Metadata-Version: 2.1
Name: pypeepa
Version: 5.4
Summary: Custom built utilities for general use
Home-page: https://github.com/IshfaqAhmedProg/PyPeepa
Author: Ishfaq Ahmed
Author-email: ishfaqahmed0837@gmail.com
Classifier: Programming Language :: Python :: 3
Classifier: License :: OSI Approved :: MIT License
Classifier: Operating System :: OS Independent
Requires-Python: >=3.6
Requires-Dist: pandas >=1.0.0
Requires-Dist: alive-progress >=1.6.0
Requires-Dist: pyfiglet >=0.8.post1
Requires-Dist: psutil >=5.9.5
Requires-Dist: chardet >=5.2.0
